nat/meta/pypi.md
nat/plugins/weave/__init__.py
nat/plugins/weave/register.py
nat/plugins/weave/weave_exporter.py
nvidia_nat_weave-1.3.1.dist-info/licenses/LICENSE-3rd-party.txt
nvidia_nat_weave-1.3.1.dist-info/licenses/LICENSE.md
nvidia_nat_weave-1.3.1.dist-info/METADATA
nvidia_nat_weave-1.3.1.dist-info/WHEEL
nvidia_nat_weave-1.3.1.dist-info/entry_points.txt
nvidia_nat_weave-1.3.1.dist-info/top_level.txt
nvidia_nat_weave-1.3.1.dist-info/RECORD
